tests/__init__.py
tests/test_main.py
yt_video_text_md/__init__.py
yt_video_text_md/audio_transcriber.py
yt_video_text_md/main.py
yt_video_text_md/transcript_processor.py
yt_video_text_md-0.1.0.dist-info/LICENSE
yt_video_text_md-0.1.0.dist-info/METADATA
yt_video_text_md-0.1.0.dist-info/WHEEL
yt_video_text_md-0.1.0.dist-info/entry_points.txt
yt_video_text_md-0.1.0.dist-info/top_level.txt
yt_video_text_md-0.1.0.dist-info/RECORD
