Metadata-Version: 2.1
Name: yt-video-text-md
Version: 0.1.0
Summary: Fetch YouTube video transcripts and save them to markdown files.
Home-page: https://github.com/kothiyarajesh/yt-video-text-md
Author: Rajesh Kothiya
Author-email: rkahir2222@gmail.com
Classifier: Programming Language :: Python :: 3
Classifier: License :: OSI Approved :: MIT License
Classifier: Operating System :: OS Independent
Requires-Python: >=3.10
License-File: LICENSE
Requires-Dist: yt-dlp
Requires-Dist: whisper
Requires-Dist: aiofiles
Requires-Dist: youtube-transcript-api
Requires-Dist: pytube
Requires-Dist: tqdm
